DockerFeed/HandlerCreator.py
DockerFeed/Main.py
DockerFeed/VerificationHandler.py
DockerFeed/__init__.py
DockerFeed/__main__.py
DockerFeed/Handlers/AbstractHandler.py
DockerFeed/Handlers/ModuleHandler.py
DockerFeed/Handlers/StackHandler.py
DockerFeed/Handlers/__init__.py
DockerFeed/Stores/AbstractStore.py
DockerFeed/Stores/FolderStore.py
DockerFeed/Stores/JfrogStore.py
DockerFeed/Stores/__init__.py
DockerFeed/Tools/ArgumentTools.py
DockerFeed/Tools/BatchProcessTools.py
DockerFeed/Tools/MainTools.py
DockerFeed/Tools/ModuleTools.py
DockerFeed/Tools/StackTools.py
DockerFeed/Tools/StackVersionTools.py
DockerFeed/Tools/SwarmInitTools.py
DockerFeed/Tools/VerificationTools.py
DockerFeed/Tools/__init__.py
DockerFeed-1.3.11.dist-info/LICENSE
DockerFeed-1.3.11.dist-info/METADATA
DockerFeed-1.3.11.dist-info/WHEEL
DockerFeed-1.3.11.dist-info/entry_points.txt
DockerFeed-1.3.11.dist-info/top_level.txt
DockerFeed-1.3.11.dist-info/RECORD
