Metadata-Version: 2.1
Name: DockerFeed
Version: 1.3.11
Summary: Docker Feed tool
Home-page: https://github.com/DIPSAS/DockerFeed
Author: DIPS AS
Author-email: hha@dips.no,heh@dips.no
License: UNKNOWN
Keywords: Docker Feed
Platform: UNKNOWN
Classifier: Development Status :: 5 - Production/Stable
Classifier: Intended Audience :: Developers
Classifier: Topic :: Software Development :: Build Tools
Classifier: License :: OSI Approved :: MIT License
Classifier: Programming Language :: Python :: 3
Classifier: Programming Language :: Python :: 3.4
Classifier: Programming Language :: Python :: 3.5
Classifier: Programming Language :: Python :: 3.6
Requires-Dist: DockerBuildSystem (>=1.1.47)
Requires-Dist: SwarmManagement (>=1.1.68)
Requires-Dist: dohq-artifactory
Requires-Dist: python-dotenv
Requires-Dist: pyyaml
Requires-Dist: requests
Requires-Dist: requirements-parser
Requires-Dist: semantic-version
Requires-Dist: validators
Provides-Extra: dev
Requires-Dist: check-manifest ; extra == 'dev'
Provides-Extra: test
Requires-Dist: coverage ; extra == 'test'
